horoscopy/__init__.py
horoscopy/freqt.py
horoscopy/math.py
horoscopy/mcep.py
horoscopy/utils.py
horoscopy/version.py
horoscopy/window.py
horoscopy-0.1.0.dist-info/LICENSE.md
horoscopy-0.1.0.dist-info/METADATA
horoscopy-0.1.0.dist-info/WHEEL
horoscopy-0.1.0.dist-info/top_level.txt
horoscopy-0.1.0.dist-info/RECORD
